ragplus/__init__.py
ragplus/__main__.py
ragplus/chunker.py
ragplus/embedder.py
ragplus/pipeline.py
ragplus/retriever.py
ragplus/utils.py
ragplus/vectorstore.py
ragplus/loaders/__init__.py
ragplus/loaders/base.py
ragplus/loaders/docx_loader.py
ragplus/loaders/pdf_loader.py
ragplus/loaders/text_loader.py
ragplus/retrieval/__init__.py
ragplus/retrieval/bm25.py
ragplus/retrieval/hybrid.py
ragplus/retrieval/reranker.py
ragplus-0.2.2.dist-info/licenses/LICENSE
ragplus-0.2.2.dist-info/METADATA
ragplus-0.2.2.dist-info/WHEEL
ragplus-0.2.2.dist-info/entry_points.txt
ragplus-0.2.2.dist-info/top_level.txt
ragplus-0.2.2.dist-info/RECORD
