Metadata-Version: 2.4
Name: ragplus
Version: 0.2.2
Summary: Lightweight, production-ready RAG toolkit with 50-70% accuracy improvements. Enhanced BM25, BGE-Base embeddings, and semantic chunking - 100% offline.
Author-email: muthuvel vishwa <muthuvelvishwa2002@gmail.com>
License: MIT
Project-URL: Homepage, https://github.com/vishwa7890/ragplus
Project-URL: Repository, https://github.com/vishwa7890/ragplus
Keywords: rag,retrieval,embeddings,vector search,nlp,llm,bm25,hybrid search,semantic chunking,bge,offline rag
Classifier: Programming Language :: Python :: 3
Classifier: Operating System :: OS Independent
Classifier: Topic :: Scientific/Engineering :: Artificial Intelligence
Requires-Python: >=3.9
License-File: LICENSE
Requires-Dist: numpy>=1.22.0
Requires-Dist: sentence-transformers>=2.2.0
Requires-Dist: torch>=2.0.0
Requires-Dist: pdfplumber>=0.9.0
Requires-Dist: python-docx>=0.8.11
Requires-Dist: rank-bm25>=0.2.2
Requires-Dist: nltk>=3.8
Requires-Dist: chardet>=5.0.0
Requires-Dist: tiktoken>=0.5.0
Requires-Dist: pytest>=8.3.4
Dynamic: license-file
